ewconfig/__init__.py
ewconfig/ewmerge.py
ewconfig/ewprune.py
ewconfig/sacpz2ew.py
ewconfig/stationxml2ew.py
ewconfig/lib/__init__.py
ewconfig/lib/args.py
ewconfig/lib/date.py
ewconfig/lib/file.py
ewconfig/lib/filter.py
ewconfig/lib/log.py
ewconfig/lib/markdown.py
ewconfig/lib/write.py
ewconfig/merge/__init__.py
ewconfig/merge/binder.py
ewconfig/merge/chan.py
ewconfig/merge/merge.py
ewconfig/merge/parser.py
ewconfig/merge/prefer.py
ewconfig/merge/rest.py
ewconfig/merge/sac.py
ewconfig/merge/slink.py
ewconfig/merge/xml.py
ewconfig/prune/__init__.py
ewconfig/prune/file.py
ewconfig/prune/response.py
ewconfig/prune/sacp.py
ewconfig/prune/xml.py
ewconfig/pz/__init__.py
ewconfig/pz/pz.py
ewconfig/pz/sac.py
ewconfig/pz/xml.py
ewconfig-1.10.dist-info/METADATA
ewconfig-1.10.dist-info/WHEEL
ewconfig-1.10.dist-info/entry_points.txt
ewconfig-1.10.dist-info/top_level.txt
ewconfig-1.10.dist-info/RECORD
