Metadata-Version: 2.1
Name: ewconfig
Version: 1.10
Summary: Create EW config from Station XML etc
Author-email: andrew cooke <andrewcooke@isti.com>
Project-URL: homepage, https://pypi.org/project/ewconfig/
Classifier: Programming Language :: Python :: 3.9
Classifier: Operating System :: OS Independent
Classifier: Development Status :: 4 - Beta
Requires-Python: >=3.9
Requires-Dist: numpy
Requires-Dist: obspy
